readretro_test1/__init__.py
readretro_test1/backup_eval.py
readretro_test1/eval.py
readretro_test1/eval_npath.py
readretro_test1/eval_single.py
readretro_test1/readretro.py
readretro_test1/retropath_eval.py
readretro_test1/run.py
readretro_test1/run_json.py
readretro_test1/run_mp.py
readretro_test1/scope2paths.py
readretro_test1/setup.py
readretro_test1-1.0.0.dist-info/LICENSE
readretro_test1-1.0.0.dist-info/METADATA
readretro_test1-1.0.0.dist-info/WHEEL
readretro_test1-1.0.0.dist-info/top_level.txt
readretro_test1-1.0.0.dist-info/RECORD
