Metadata-Version: 2.1
Name: readretro_test1
Version: 1.0.0
Summary: READRetro lib test
Home-page: https://github.com/SeulLee05/READRetro
Author: Taein Kim
Author-email: tedori725@kaist.ac.kr
Project-URL: Bug Tracker, https://github.com/SeulLee05/issues
Classifier: Programming Language :: Python :: 3
Classifier: License :: OSI Approved :: MIT License
Classifier: Operating System :: OS Independent
Requires-Python: >=3.8
License-File: LICENSE
